WestCoastAD/__init__.py
WestCoastAD/src/__init__.py
WestCoastAD/src/forward_mode_AD.py
WestCoastAD/src/forward_mode_AD_auxiliaries.py
WestCoastAD/src/initializer.py
WestCoastAD/src/optimizer.py
WestCoastAD/test/__init__.py
WestCoastAD/test/forward_mode_AD_auxiliaries_test.py
WestCoastAD/test/forward_mode_AD_test.py
WestCoastAD/test/initializer_test.py
WestCoastAD/test/optimizer_test.py
WestCoastAD-1.0.dist-info/METADATA
WestCoastAD-1.0.dist-info/WHEEL
WestCoastAD-1.0.dist-info/top_level.txt
WestCoastAD-1.0.dist-info/RECORD
