Metadata-Version: 2.1
Name: WestCoastAD
Version: 1.0
Summary: An Optimization Package with an Automatic Differenation Core
Home-page: https://github.com/West-Coast-Differentiators/cs107-FinalProject
Author: Anita Mahinpei, Yingchen Liu, Erik Adames, Lekshmi Santhosh
License: UNKNOWN
Platform: UNKNOWN
Classifier: Programming Language :: Python :: 3
Classifier: Operating System :: OS Independent
Requires-Python: >=3.6
Requires-Dist: numpy (==1.19.3)
